setup.py
text2pdf/__init__.py
text2pdf/text2pdf
text2pdf/text2pdfgui
text2pdf.egg-info/PKG-INFO
text2pdf.egg-info/SOURCES.txt
text2pdf.egg-info/dependency_links.txt
text2pdf.egg-info/requires.txt
text2pdf.egg-info/top_level.txt