Metadata-Version: 1.1
Name: text2pdf
Version: 0.2
Summary: Tools to convert text files to PDF
Home-page: https://github.com/tedlaz/text2pdf
Author: Ted Lazaros
Author-email: tedlaz@gmail.com
License: GPLv3
Keywords: PDF,gui,pyqt5
Platform: UNKNOWN
Classifier: Development Status :: 4 - Beta
Classifier: Environment :: Console
Classifier: Environment :: X11 Applications :: Qt
Classifier: Environment :: Win32 (MS Windows)
Classifier: Intended Audience :: Developers
Classifier: Natural Language :: English
Classifier: Operating System :: OS Independent
Classifier: Programming Language :: Python
Classifier: Programming Language :: Python :: 3
Classifier: Programming Language :: Python :: 3 :: Only
Classifier: Programming Language :: Python :: 3.5
Classifier: Programming Language :: Python :: 3.6
Classifier: Topic :: Utilities
